onesecmail/__init__.py
onesecmail/__version__.py
onesecmail/mail.py
onesecmail/message.py
onesecmail/utils.py
onesecmail/validators.py
onesecmail-0.0.1.dist-info/LICENSE
onesecmail-0.0.1.dist-info/METADATA
onesecmail-0.0.1.dist-info/WHEEL
onesecmail-0.0.1.dist-info/top_level.txt
onesecmail-0.0.1.dist-info/RECORD
