Metadata-Version: 2.1
Name: onesecmail
Version: 0.0.1
Summary: The unofficial Python client for the 1secmail API.
Home-page: https://github.com/yyyyyyyan/onesecmail
Author: yyyyyyyan
Author-email: contact@yyyyyyyan.tech
License: MIT
Download-URL: https://github.com/yyyyyyyan/onesecmail/archive/refs/heads/main.zip
Keywords: email,1secmail
Platform: UNKNOWN
Classifier: Development Status :: 4 - Beta
Classifier: Intended Audience :: Developers
Classifier: License :: OSI Approved :: MIT License
Classifier: Operating System :: OS Independent
Classifier: Programming Language :: Python
Classifier: Programming Language :: Python :: 3
Classifier: Programming Language :: Python :: 3.6
Classifier: Programming Language :: Python :: 3.7
Classifier: Programming Language :: Python :: 3.8
Classifier: Programming Language :: Python :: 3.9
Classifier: Programming Language :: Python :: 3.10
Classifier: Topic :: Communications :: Email
Classifier: Topic :: Software Development :: Libraries
License-File: LICENSE
Requires-Dist: requests (>=2.25.1)
